django_static_underscore_i18n-1.9.1.dist-info/DESCRIPTION.rst
django_static_underscore_i18n-1.9.1.dist-info/METADATA
django_static_underscore_i18n-1.9.1.dist-info/metadata.json
django_static_underscore_i18n-1.9.1.dist-info/RECORD
django_static_underscore_i18n-1.9.1.dist-info/top_level.txt
django_static_underscore_i18n-1.9.1.dist-info/WHEEL
staticunderscorei18n/__init__.py
staticunderscorei18n/conf.py
staticunderscorei18n/render.py
staticunderscorei18n/utils.py
staticunderscorei18n/management/__init__.py
staticunderscorei18n/management/commands/__init__.py
staticunderscorei18n/management/commands/compilejsunderscorei18n.py
