Metadata-Version: 2.0
Name: django-static-underscore-i18n
Version: 1.9.1
Summary: A Django app that provides helper for generating Javascript Underscore templates to static files with i18n support.
Home-page: http://django-static-underscore-i18n.readthedocs.org/
Author: Dmytro Voloshyn
Author-email: dmytro@preply.com
License: BSD
Download-URL: https://github.com/cubicova17/django-static-underscore-i18n/tarball/1.9
Platform: UNKNOWN
Classifier: Development Status :: 5 - Production/Stable
Classifier: Environment :: Web Environment
Classifier: Framework :: Django
Classifier: Intended Audience :: Developers
Classifier: License :: OSI Approved :: BSD License
Classifier: Operating System :: OS Independent
Classifier: Programming Language :: Python
Classifier: Programming Language :: Python :: 2
Classifier: Programming Language :: Python :: 2.6
Classifier: Programming Language :: Python :: 2.7
Requires-Dist: Django (>=1.4)
Requires-Dist: django-appconf (>=0.4)
